Metadata-Version: 2.1
Name: distributions-m
Version: 0.1
Summary: Distributions
Home-page: UNKNOWN
License: UNKNOWN
Platform: UNKNOWN
